<?xml version="1.0" encoding="ISO-8859-1" standalone="yes"?>
<?xml-stylesheet type="text/xsl" href="../../../clonk.xsl"?>
<clonkDoc xmlns="https://clonkspot.org"
      xmlns:xsi="http://www.w3.org/2001/XMLSchema-instance"
          xsi:schemaLocation="https://clonkspot.org ../../../clonk.xsd" xml:lang="de">
	<func isAsync="false">
		<title>SetMass</title>
		<category>Objekte/Status</category>
		<versions><version>4.9.1.0 GWE</version></versions>
		<syntax>
			<rtype isReference="false">bool</rtype>
			<params>
				<param isReference="false" isOptional="false"><type>int</type><name>iNewMass</name><desc>Neue Eigenmasse</desc></param>
				<param isReference="false" isOptional="true"><type>object</type><name>pObj</name><desc>Objekt, dessen Eigenmasse geändert werden soll. 0 bei lokalem Aufruf.</desc></param>
			</params>
		</syntax>
		<desc>Ändert die Eigenmasse eines Objekts. Die Eigenmasse entspricht dem in der <emLink href="definition/defcore.html">DefCore.txt</emLink> angegebenen Wert unter [DefCore], Mass. Die tatsächliche Objektmasse ergibt sich durch Hinzurechnen der Masse aller enthaltenen Objekte.</desc>
		<examples>
			<example>

<code>private func GetOwnMass(pClonk)
  {
  var iMass=<funcLink>GetMass</funcLink>(pClonk), i, pObj;
  <funcLink>while</funcLink>(pObj = <funcLink>Contents</funcLink>(i++, pClonk)) iMass -= <funcLink>GetMass</funcLink>(pObj);
  <funcLink>return</funcLink>(iMass);
  }

protected func Activate(pByClonk)
  {
  [Essen]
  SetMass(GetOwnMass(pByClonk) + 100, pByClonk);
  <funcLink>Sound</funcLink>("ClonkMunch", 0, pByClonk);
  <funcLink>return</funcLink>(<funcLink>RemoveObject</funcLink>());
  }</code>

				<text>Script für einen Keks: Beim Essen nimmt die Masse des Clonks zu.</text>
			</example>
		</examples>
		<related>
			<funcLink>GetMass</funcLink>
		</related>
	</func>
	<author>Sven2</author><date>2003-06</date>
</clonkDoc>
